[{
    "name" : "Adventure Capitalist!",
    "cover" : "adventurecapitalist.jpg",

    "platforms" : ["iOS", "macOS"],

    "achievements" :
    [{
        "name" : "GameCenter",
        "total" : "32",
        "completed" : "32"
    },
    {
        "name" : "Steam",
        "total" : "31",
        "completed" : "31"

    }],

    "notes" : ""
},
{
    "name" : "Assassin's Creed 2",
    "cover" : "assassinscreed2.jpg",

    "platforms" : ["macOS"],

    "achievements" : [],

    "notes" : ""
},
{
    "name" : "Duke of Alpha Centauri",
    "cover" : "dukeofalphacentauri.jpg",

    "platforms" : ["macOS"],

    "achievements" :
    [{
        "name" : "Steam",
        "total" : "128",
        "completed" : "128"

    }],

    "notes" : ""
},
{
    "name" : "SPACEPLAN",
    "cover" : "spaceplan.jpg",

    "platforms" : ["macOS"],

    "achievements" : [],

    "notes" : ""
}]
